<?xml version="1.0" encoding="UTF-8"?>
<!DOCTYPE mapper PUBLIC "-//mybatis.org//DTD Mapper 3.0//EN" "http://mybatis.org/dtd/mybatis-3-mapper.dtd">
<mapper namespace="com.shineon.coder.db.dao.ShineonUserMapper">
  <resultMap id="BaseResultMap" type="com.shineon.coder.db.pojo.ShineonUser">
    <!--
      WARNING - @mbggenerated
      This element is automatically generated by MyBatis Generator, do not modify.
      This element was generated on Thu Jun 20 16:36:21 CST 2019.
    -->
    <id column="id" jdbcType="INTEGER" property="id" />
    <result column="username" jdbcType="VARCHAR" property="username" />
    <result column="password" jdbcType="VARCHAR" property="password" />
    <result column="displayName" jdbcType="VARCHAR" property="displayname" />
    <result column="parent" jdbcType="INTEGER" property="parent" />
    <result column="usercode" jdbcType="VARCHAR" property="usercode" />
    <result column="userthumb" jdbcType="VARCHAR" property="userthumb" />
    <result column="telephone" jdbcType="VARCHAR" property="telephone" />
    <result column="usermark" jdbcType="VARCHAR" property="usermark" />
    <result column="userType" jdbcType="TINYINT" property="usertype" />
    <result column="admin" jdbcType="TINYINT" property="admin" />
    <result column="timeCreated" jdbcType="TIMESTAMP" property="timecreated" />
    <result column="timeModified" jdbcType="TIMESTAMP" property="timemodified" />
    <result column="timeDeleted" jdbcType="TIMESTAMP" property="timedeleted" />
    <result column="flagDeleted" jdbcType="TINYINT" property="flagdeleted" />
    <result column="timeLimit" jdbcType="TIMESTAMP" property="timelimit" />
    <result column="countLimit" jdbcType="TINYINT" property="countlimit" />
  </resultMap>
  <sql id="Example_Where_Clause">
    <!--
      WARNING - @mbggenerated
      This element is automatically generated by MyBatis Generator, do not modify.
      This element was generated on Thu Jun 20 16:36:21 CST 2019.
    -->
    <where>
      <foreach collection="oredCriteria" item="criteria" separator="or">
        <if test="criteria.valid">
          <trim prefix="(" prefixOverrides="and" suffix=")">
            <foreach collection="criteria.criteria" item="criterion">
              <choose>
                <when test="criterion.noValue">
                  and ${criterion.condition}
                </when>
                <when test="criterion.singleValue">
                  and ${criterion.condition} #{criterion.value}
                </when>
                <when test="criterion.betweenValue">
                  and ${criterion.condition} #{criterion.value} and #{criterion.secondValue}
                </when>
                <when test="criterion.listValue">
                  and ${criterion.condition}
                  <foreach close=")" collection="criterion.value" item="listItem" open="(" separator=",">
                    #{listItem}
                  </foreach>
                </when>
              </choose>
            </foreach>
          </trim>
        </if>
      </foreach>
    </where>
  </sql>
  <sql id="Update_By_Example_Where_Clause">
    <!--
      WARNING - @mbggenerated
      This element is automatically generated by MyBatis Generator, do not modify.
      This element was generated on Thu Jun 20 16:36:21 CST 2019.
    -->
    <where>
      <foreach collection="example.oredCriteria" item="criteria" separator="or">
        <if test="criteria.valid">
          <trim prefix="(" prefixOverrides="and" suffix=")">
            <foreach collection="criteria.criteria" item="criterion">
              <choose>
                <when test="criterion.noValue">
                  and ${criterion.condition}
                </when>
                <when test="criterion.singleValue">
                  and ${criterion.condition} #{criterion.value}
                </when>
                <when test="criterion.betweenValue">
                  and ${criterion.condition} #{criterion.value} and #{criterion.secondValue}
                </when>
                <when test="criterion.listValue">
                  and ${criterion.condition}
                  <foreach close=")" collection="criterion.value" item="listItem" open="(" separator=",">
                    #{listItem}
                  </foreach>
                </when>
              </choose>
            </foreach>
          </trim>
        </if>
      </foreach>
    </where>
  </sql>
  <sql id="Base_Column_List">
    <!--
      WARNING - @mbggenerated
      This element is automatically generated by MyBatis Generator, do not modify.
      This element was generated on Thu Jun 20 16:36:21 CST 2019.
    -->
    id, username, password, displayName, parent, usercode, userthumb, telephone, usermark, 
    userType, admin, timeCreated, timeModified, timeDeleted, flagDeleted, timeLimit, 
    countLimit
  </sql>
  <select id="selectByExample" parameterType="com.shineon.coder.db.pojo.ShineonUserExample" resultMap="BaseResultMap">
    <!--
      WARNING - @mbggenerated
      This element is automatically generated by MyBatis Generator, do not modify.
      This element was generated on Thu Jun 20 16:36:21 CST 2019.
    -->
    select
    <if test="distinct">
      distinct
    </if>
    <include refid="Base_Column_List" />
    from shineon_user
    <if test="_parameter != null">
      <include refid="Example_Where_Clause" />
    </if>
    <if test="orderByClause != null">
      order by ${orderByClause}
    </if>
  </select>
  <select id="selectByPrimaryKey" parameterType="java.lang.Integer" resultMap="BaseResultMap">
    <!--
      WARNING - @mbggenerated
      This element is automatically generated by MyBatis Generator, do not modify.
      This element was generated on Thu Jun 20 16:36:21 CST 2019.
    -->
    select 
    <include refid="Base_Column_List" />
    from shineon_user
    where id = #{id,jdbcType=INTEGER}
  </select>
  <delete id="deleteByPrimaryKey" parameterType="java.lang.Integer">
    <!--
      WARNING - @mbggenerated
      This element is automatically generated by MyBatis Generator, do not modify.
      This element was generated on Thu Jun 20 16:36:21 CST 2019.
    -->
    delete from shineon_user
    where id = #{id,jdbcType=INTEGER}
  </delete>
  <delete id="deleteByExample" parameterType="com.shineon.coder.db.pojo.ShineonUserExample">
    <!--
      WARNING - @mbggenerated
      This element is automatically generated by MyBatis Generator, do not modify.
      This element was generated on Thu Jun 20 16:36:21 CST 2019.
    -->
    delete from shineon_user
    <if test="_parameter != null">
      <include refid="Example_Where_Clause" />
    </if>
  </delete>
  <insert id="insert" parameterType="com.shineon.coder.db.pojo.ShineonUser">
    <!--
      WARNING - @mbggenerated
      This element is automatically generated by MyBatis Generator, do not modify.
      This element was generated on Thu Jun 20 16:36:21 CST 2019.
    -->
    insert into shineon_user (id, username, password, 
      displayName, parent, usercode, 
      userthumb, telephone, usermark, 
      userType, admin, timeCreated, 
      timeModified, timeDeleted, flagDeleted, 
      timeLimit, countLimit)
    values (#{id,jdbcType=INTEGER}, #{username,jdbcType=VARCHAR}, #{password,jdbcType=VARCHAR}, 
      #{displayname,jdbcType=VARCHAR}, #{parent,jdbcType=INTEGER}, #{usercode,jdbcType=VARCHAR}, 
      #{userthumb,jdbcType=VARCHAR}, #{telephone,jdbcType=VARCHAR}, #{usermark,jdbcType=VARCHAR}, 
      #{usertype,jdbcType=TINYINT}, #{admin,jdbcType=TINYINT}, #{timecreated,jdbcType=TIMESTAMP}, 
      #{timemodified,jdbcType=TIMESTAMP}, #{timedeleted,jdbcType=TIMESTAMP}, #{flagdeleted,jdbcType=TINYINT}, 
      #{timelimit,jdbcType=TIMESTAMP}, #{countlimit,jdbcType=TINYINT})
  </insert>
  <insert id="insertSelective" parameterType="com.shineon.coder.db.pojo.ShineonUser">
    <!--
      WARNING - @mbggenerated
      This element is automatically generated by MyBatis Generator, do not modify.
      This element was generated on Thu Jun 20 16:36:21 CST 2019.
    -->
    insert into shineon_user
    <trim prefix="(" suffix=")" suffixOverrides=",">
      <if test="id != null">
        id,
      </if>
      <if test="username != null">
        username,
      </if>
      <if test="password != null">
        password,
      </if>
      <if test="displayname != null">
        displayName,
      </if>
      <if test="parent != null">
        parent,
      </if>
      <if test="usercode != null">
        usercode,
      </if>
      <if test="userthumb != null">
        userthumb,
      </if>
      <if test="telephone != null">
        telephone,
      </if>
      <if test="usermark != null">
        usermark,
      </if>
      <if test="usertype != null">
        userType,
      </if>
      <if test="admin != null">
        admin,
      </if>
      <if test="timecreated != null">
        timeCreated,
      </if>
      <if test="timemodified != null">
        timeModified,
      </if>
      <if test="timedeleted != null">
        timeDeleted,
      </if>
      <if test="flagdeleted != null">
        flagDeleted,
      </if>
      <if test="timelimit != null">
        timeLimit,
      </if>
      <if test="countlimit != null">
        countLimit,
      </if>
    </trim>
    <trim prefix="values (" suffix=")" suffixOverrides=",">
      <if test="id != null">
        #{id,jdbcType=INTEGER},
      </if>
      <if test="username != null">
        #{username,jdbcType=VARCHAR},
      </if>
      <if test="password != null">
        #{password,jdbcType=VARCHAR},
      </if>
      <if test="displayname != null">
        #{displayname,jdbcType=VARCHAR},
      </if>
      <if test="parent != null">
        #{parent,jdbcType=INTEGER},
      </if>
      <if test="usercode != null">
        #{usercode,jdbcType=VARCHAR},
      </if>
      <if test="userthumb != null">
        #{userthumb,jdbcType=VARCHAR},
      </if>
      <if test="telephone != null">
        #{telephone,jdbcType=VARCHAR},
      </if>
      <if test="usermark != null">
        #{usermark,jdbcType=VARCHAR},
      </if>
      <if test="usertype != null">
        #{usertype,jdbcType=TINYINT},
      </if>
      <if test="admin != null">
        #{admin,jdbcType=TINYINT},
      </if>
      <if test="timecreated != null">
        #{timecreated,jdbcType=TIMESTAMP},
      </if>
      <if test="timemodified != null">
        #{timemodified,jdbcType=TIMESTAMP},
      </if>
      <if test="timedeleted != null">
        #{timedeleted,jdbcType=TIMESTAMP},
      </if>
      <if test="flagdeleted != null">
        #{flagdeleted,jdbcType=TINYINT},
      </if>
      <if test="timelimit != null">
        #{timelimit,jdbcType=TIMESTAMP},
      </if>
      <if test="countlimit != null">
        #{countlimit,jdbcType=TINYINT},
      </if>
    </trim>
  </insert>
  <select id="countByExample" parameterType="com.shineon.coder.db.pojo.ShineonUserExample" resultType="java.lang.Integer">
    <!--
      WARNING - @mbggenerated
      This element is automatically generated by MyBatis Generator, do not modify.
      This element was generated on Thu Jun 20 16:36:21 CST 2019.
    -->
    select count(*) from shineon_user
    <if test="_parameter != null">
      <include refid="Example_Where_Clause" />
    </if>
  </select>
  <update id="updateByExampleSelective" parameterType="map">
    <!--
      WARNING - @mbggenerated
      This element is automatically generated by MyBatis Generator, do not modify.
      This element was generated on Thu Jun 20 16:36:21 CST 2019.
    -->
    update shineon_user
    <set>
      <if test="record.id != null">
        id = #{record.id,jdbcType=INTEGER},
      </if>
      <if test="record.username != null">
        username = #{record.username,jdbcType=VARCHAR},
      </if>
      <if test="record.password != null">
        password = #{record.password,jdbcType=VARCHAR},
      </if>
      <if test="record.displayname != null">
        displayName = #{record.displayname,jdbcType=VARCHAR},
      </if>
      <if test="record.parent != null">
        parent = #{record.parent,jdbcType=INTEGER},
      </if>
      <if test="record.usercode != null">
        usercode = #{record.usercode,jdbcType=VARCHAR},
      </if>
      <if test="record.userthumb != null">
        userthumb = #{record.userthumb,jdbcType=VARCHAR},
      </if>
      <if test="record.telephone != null">
        telephone = #{record.telephone,jdbcType=VARCHAR},
      </if>
      <if test="record.usermark != null">
        usermark = #{record.usermark,jdbcType=VARCHAR},
      </if>
      <if test="record.usertype != null">
        userType = #{record.usertype,jdbcType=TINYINT},
      </if>
      <if test="record.admin != null">
        admin = #{record.admin,jdbcType=TINYINT},
      </if>
      <if test="record.timecreated != null">
        timeCreated = #{record.timecreated,jdbcType=TIMESTAMP},
      </if>
      <if test="record.timemodified != null">
        timeModified = #{record.timemodified,jdbcType=TIMESTAMP},
      </if>
      <if test="record.timedeleted != null">
        timeDeleted = #{record.timedeleted,jdbcType=TIMESTAMP},
      </if>
      <if test="record.flagdeleted != null">
        flagDeleted = #{record.flagdeleted,jdbcType=TINYINT},
      </if>
      <if test="record.timelimit != null">
        timeLimit = #{record.timelimit,jdbcType=TIMESTAMP},
      </if>
      <if test="record.countlimit != null">
        countLimit = #{record.countlimit,jdbcType=TINYINT},
      </if>
    </set>
    <if test="_parameter != null">
      <include refid="Update_By_Example_Where_Clause" />
    </if>
  </update>
  <update id="updateByExample" parameterType="map">
    <!--
      WARNING - @mbggenerated
      This element is automatically generated by MyBatis Generator, do not modify.
      This element was generated on Thu Jun 20 16:36:21 CST 2019.
    -->
    update shineon_user
    set id = #{record.id,jdbcType=INTEGER},
      username = #{record.username,jdbcType=VARCHAR},
      password = #{record.password,jdbcType=VARCHAR},
      displayName = #{record.displayname,jdbcType=VARCHAR},
      parent = #{record.parent,jdbcType=INTEGER},
      usercode = #{record.usercode,jdbcType=VARCHAR},
      userthumb = #{record.userthumb,jdbcType=VARCHAR},
      telephone = #{record.telephone,jdbcType=VARCHAR},
      usermark = #{record.usermark,jdbcType=VARCHAR},
      userType = #{record.usertype,jdbcType=TINYINT},
      admin = #{record.admin,jdbcType=TINYINT},
      timeCreated = #{record.timecreated,jdbcType=TIMESTAMP},
      timeModified = #{record.timemodified,jdbcType=TIMESTAMP},
      timeDeleted = #{record.timedeleted,jdbcType=TIMESTAMP},
      flagDeleted = #{record.flagdeleted,jdbcType=TINYINT},
      timeLimit = #{record.timelimit,jdbcType=TIMESTAMP},
      countLimit = #{record.countlimit,jdbcType=TINYINT}
    <if test="_parameter != null">
      <include refid="Update_By_Example_Where_Clause" />
    </if>
  </update>
  <update id="updateByPrimaryKeySelective" parameterType="com.shineon.coder.db.pojo.ShineonUser">
    <!--
      WARNING - @mbggenerated
      This element is automatically generated by MyBatis Generator, do not modify.
      This element was generated on Thu Jun 20 16:36:21 CST 2019.
    -->
    update shineon_user
    <set>
      <if test="username != null">
        username = #{username,jdbcType=VARCHAR},
      </if>
      <if test="password != null">
        password = #{password,jdbcType=VARCHAR},
      </if>
      <if test="displayname != null">
        displayName = #{displayname,jdbcType=VARCHAR},
      </if>
      <if test="parent != null">
        parent = #{parent,jdbcType=INTEGER},
      </if>
      <if test="usercode != null">
        usercode = #{usercode,jdbcType=VARCHAR},
      </if>
      <if test="userthumb != null">
        userthumb = #{userthumb,jdbcType=VARCHAR},
      </if>
      <if test="telephone != null">
        telephone = #{telephone,jdbcType=VARCHAR},
      </if>
      <if test="usermark != null">
        usermark = #{usermark,jdbcType=VARCHAR},
      </if>
      <if test="usertype != null">
        userType = #{usertype,jdbcType=TINYINT},
      </if>
      <if test="admin != null">
        admin = #{admin,jdbcType=TINYINT},
      </if>
      <if test="timecreated != null">
        timeCreated = #{timecreated,jdbcType=TIMESTAMP},
      </if>
      <if test="timemodified != null">
        timeModified = #{timemodified,jdbcType=TIMESTAMP},
      </if>
      <if test="timedeleted != null">
        timeDeleted = #{timedeleted,jdbcType=TIMESTAMP},
      </if>
      <if test="flagdeleted != null">
        flagDeleted = #{flagdeleted,jdbcType=TINYINT},
      </if>
      <if test="timelimit != null">
        timeLimit = #{timelimit,jdbcType=TIMESTAMP},
      </if>
      <if test="countlimit != null">
        countLimit = #{countlimit,jdbcType=TINYINT},
      </if>
    </set>
    where id = #{id,jdbcType=INTEGER}
  </update>
  <update id="updateByPrimaryKey" parameterType="com.shineon.coder.db.pojo.ShineonUser">
    <!--
      WARNING - @mbggenerated
      This element is automatically generated by MyBatis Generator, do not modify.
      This element was generated on Thu Jun 20 16:36:21 CST 2019.
    -->
    update shineon_user
    set username = #{username,jdbcType=VARCHAR},
      password = #{password,jdbcType=VARCHAR},
      displayName = #{displayname,jdbcType=VARCHAR},
      parent = #{parent,jdbcType=INTEGER},
      usercode = #{usercode,jdbcType=VARCHAR},
      userthumb = #{userthumb,jdbcType=VARCHAR},
      telephone = #{telephone,jdbcType=VARCHAR},
      usermark = #{usermark,jdbcType=VARCHAR},
      userType = #{usertype,jdbcType=TINYINT},
      admin = #{admin,jdbcType=TINYINT},
      timeCreated = #{timecreated,jdbcType=TIMESTAMP},
      timeModified = #{timemodified,jdbcType=TIMESTAMP},
      timeDeleted = #{timedeleted,jdbcType=TIMESTAMP},
      flagDeleted = #{flagdeleted,jdbcType=TINYINT},
      timeLimit = #{timelimit,jdbcType=TIMESTAMP},
      countLimit = #{countlimit,jdbcType=TINYINT}
    where id = #{id,jdbcType=INTEGER}
  </update>
</mapper>